LICENSE
MANIFEST.in
README.md
pyproject.toml
setup.py
./dyncfs/__init__.py
./dyncfs/cfs_dynamic.py
./dyncfs/cfs_dynamic_backup.py
./dyncfs/cfs_static.py
./dyncfs/configuration.py
./dyncfs/convert_input_format.py
./dyncfs/create_edcmp.py
./dyncfs/create_edcmp_bulk.py
./dyncfs/create_edgrn.py
./dyncfs/create_edgrn_bulk.py
./dyncfs/create_nd_by_crust1_ak135.py
./dyncfs/create_qseis2025.py
./dyncfs/create_qseis2025_bulk.py
./dyncfs/create_qssp2020.py
./dyncfs/create_qssp2020_bulk.py
./dyncfs/crust1.py
./dyncfs/edcmp2inp.py
./dyncfs/edgrn2inp.py
./dyncfs/focal_mechanism.py
./dyncfs/geo.py
./dyncfs/main.py
./dyncfs/obspy_geo.py
./dyncfs/plot_cfs_dynamic_2d.py
./dyncfs/plot_cfs_dynamic_3d.py
./dyncfs/plot_cfs_static_2d.py
./dyncfs/plot_cfs_static_3d.py
./dyncfs/plot_gif.py
./dyncfs/plot_slip_2d.py
./dyncfs/plot_slip_3d.py
./dyncfs/pytaup.py
./dyncfs/qseis2025inp.py
./dyncfs/qssp2020inp.py
./dyncfs/read_edcmp.py
./dyncfs/read_qseis2025.py
./dyncfs/read_qssp2020.py
./dyncfs/signal_process.py
./dyncfs/utils.py
./dyncfs/exec/TauP-2.6.1.jar
dyncfs/__init__.py
dyncfs/cfs_dynamic.py
dyncfs/cfs_dynamic_backup.py
dyncfs/cfs_static.py
dyncfs/configuration.py
dyncfs/convert_input_format.py
dyncfs/create_edcmp.py
dyncfs/create_edcmp_bulk.py
dyncfs/create_edgrn.py
dyncfs/create_edgrn_bulk.py
dyncfs/create_nd_by_crust1_ak135.py
dyncfs/create_qseis2025.py
dyncfs/create_qseis2025_bulk.py
dyncfs/create_qssp2020.py
dyncfs/create_qssp2020_bulk.py
dyncfs/crust1.py
dyncfs/edcmp2inp.py
dyncfs/edgrn2inp.py
dyncfs/focal_mechanism.py
dyncfs/geo.py
dyncfs/main.py
dyncfs/obspy_geo.py
dyncfs/plot_cfs_dynamic_2d.py
dyncfs/plot_cfs_dynamic_3d.py
dyncfs/plot_cfs_static_2d.py
dyncfs/plot_cfs_static_3d.py
dyncfs/plot_gif.py
dyncfs/plot_slip_2d.py
dyncfs/plot_slip_3d.py
dyncfs/pytaup.py
dyncfs/qseis2025inp.py
dyncfs/qssp2020inp.py
dyncfs/read_edcmp.py
dyncfs/read_qseis2025.py
dyncfs/read_qssp2020.py
dyncfs/signal_process.py
dyncfs/utils.py
dyncfs.egg-info/PKG-INFO
dyncfs.egg-info/SOURCES.txt
dyncfs.egg-info/dependency_links.txt
dyncfs.egg-info/entry_points.txt
dyncfs.egg-info/requires.txt
dyncfs.egg-info/top_level.txt
dyncfs/exec/TauP-2.6.1.jar
fortran_src_codes/edcmp2.0_src/dc3d.f
